CHANGES.txt
LICENSE.txt
README.txt
bootstrap.py
buildout.cfg
setup.py
src/z3c/__init__.py
src/z3c.layer.trusted.egg-info/PKG-INFO
src/z3c.layer.trusted.egg-info/SOURCES.txt
src/z3c.layer.trusted.egg-info/dependency_links.txt
src/z3c.layer.trusted.egg-info/namespace_packages.txt
src/z3c.layer.trusted.egg-info/not-zip-safe
src/z3c.layer.trusted.egg-info/requires.txt
src/z3c.layer.trusted.egg-info/top_level.txt
src/z3c/layer/__init__.py
src/z3c/layer/trusted/README.txt
src/z3c/layer/trusted/__init__.py
src/z3c/layer/trusted/configure.zcml
src/z3c/layer/trusted/ftesting.zcml
src/z3c/layer/trusted/tests.py
src/z3c/layer/trusted/z3c.layer.trusted-configure.zcml
src/z3c/layer/trusted/zope.traversing.browser.zcml